{
  "project_info": {
    "project_number": "404556422786",
    "firebase_url": "https://namu-c1af6-default-rtdb.firebaseio.com",
    "project_id": "namu-c1af6",
    "storage_bucket": "namu-c1af6.firebasestorage.app"
  },
  "client": [
    {
      "client_info": {
        "mobilesdk_app_id": "1:404556422786:android:07bcac78c80e8cc5305e9b",
        "android_client_info": {
          "package_name": "com.example.sigi"
        }
      },
      "oauth_client": [],
      "api_key": [
        {
          "current_key": "AIzaSyDlCqSArDoGkitxB-y-T1BudfRiO-0guLU"
        }
      ],
      "services": {
        "appinvite_service": {
          "other_platform_oauth_client": []
        }
      }
    }
  ],
  "configuration_version": "1"
}